torching/__init__.py
torching/flash_attention/03-matrix-multiplication-all-types.py
torching/flash_attention/06-fused-attention-fwd-transV.py
torching/flash_attention/06-fused-attention-transV.py
torching/flash_attention/__init__.py
torching/flash_attention/flash-attention.py
torching/flash_attention/hbm-bw-test.py
torching-0.0.1.dist-info/LICENSE
torching-0.0.1.dist-info/METADATA
torching-0.0.1.dist-info/WHEEL
torching-0.0.1.dist-info/top_level.txt
torching-0.0.1.dist-info/RECORD
